bench/__init__.py
bench/run.py
bench/eval/__init__.py
bench/eval/magic_html.py
bench/eval/ours.py
bench/eval/unstructured_eval.py
jupyter/__init__.py
jupyter/domain_clustering/__init__.py
llm_web_kit/__init__.py
llm_web_kit/simple.py
llm_web_kit/__pycache__/__init__.cpython-310.pyc
llm_web_kit/api/DATABASE_README.md
llm_web_kit/api/README.md
llm_web_kit/api/__init__.py
llm_web_kit/api/database.py
llm_web_kit/api/database_setup.sql
llm_web_kit/api/dependencies.py
llm_web_kit/api/main.py
llm_web_kit/api/requirements.txt
llm_web_kit/api/run_server.py
llm_web_kit/api/models/__init__.py
llm_web_kit/api/models/db_models.py
llm_web_kit/api/models/request.py
llm_web_kit/api/models/response.py
llm_web_kit/api/routers/__init__.py
llm_web_kit/api/routers/htmls.py
llm_web_kit/api/services/__init__.py
llm_web_kit/api/services/html_service.py
llm_web_kit/api/services/inference_service.py
llm_web_kit/config/README.MD
llm_web_kit/config/__init__.py
llm_web_kit/config/cfg_reader.py
llm_web_kit/config/pipe_tpl/ebook.jsonc
llm_web_kit/config/pipe_tpl/html-test.jsonc
llm_web_kit/config/pipe_tpl/html.jsonc
llm_web_kit/config/pipe_tpl/layout_batch_html.jsonc
llm_web_kit/config/pipe_tpl/layout_batch_noclip_html.jsonc
llm_web_kit/config/pipe_tpl/llm_html.jsonc
llm_web_kit/config/pipe_tpl/llm_noclip_html.jsonc
llm_web_kit/config/pipe_tpl/magic_html.jsonc
llm_web_kit/config/pipe_tpl/magic_html_noclip_html.jsonc
llm_web_kit/config/pipe_tpl/main_html_test.jsonc
llm_web_kit/config/pipe_tpl/model.jsonc
llm_web_kit/config/pipe_tpl/noclip_html.jsonc
llm_web_kit/config/pipe_tpl/noclip_html_test.jsonc
llm_web_kit/config/pipe_tpl/pdf.jsonc
llm_web_kit/dataio/__init__.py
llm_web_kit/dataio/base.py
llm_web_kit/dataio/filebase.py
llm_web_kit/exception/__init__.py
llm_web_kit/exception/exception.jsonc
llm_web_kit/exception/exception.py
llm_web_kit/extractor/__init__.py
llm_web_kit/extractor/base.py
llm_web_kit/extractor/config.py
llm_web_kit/extractor/extractor.py
llm_web_kit-4.2.1.dist-info/METADATA
llm_web_kit-4.2.1.dist-info/WHEEL
llm_web_kit-4.2.1.dist-info/entry_points.txt
llm_web_kit-4.2.1.dist-info/top_level.txt
llm_web_kit-4.2.1.dist-info/RECORD
