Metadata-Version: 2.4
Name: llm_web_kit
Version: 4.2.1
Summary: LLM Web Kit for processing web content
Home-page: https://github.com/ccprocessor/llm_web_kit
Requires-Python: >=3.10, <3.14
Requires-Dist: aiohttp==3.12.15
Requires-Dist: beautifulsoup4>=4.12.2
Requires-Dist: boto3==1.28.43
Requires-Dist: cairosvg==2.7.1
Requires-Dist: click==8.1.8
Requires-Dist: commentjson==0.9.0
Requires-Dist: fastapi==0.116.1
Requires-Dist: fasttext-wheel==0.9.2
Requires-Dist: filelock==3.16.1
Requires-Dist: html-alg-lib==2.0.2
Requires-Dist: jieba-fast==0.53
Requires-Dist: jupyter==1.1.1
Requires-Dist: langdetect_zh==1.0.4
Requires-Dist: lightgbm==4.5.0
Requires-Dist: loguru==0.7.2
Requires-Dist: lxml<=5.3.0
Requires-Dist: lxml_html_clean==0.4.2
Requires-Dist: nbconvert==7.16.6
Requires-Dist: nltk==3.8.1
Requires-Dist: notebook==7.4.2
Requires-Dist: numpy==1.26.4
Requires-Dist: optimum==1.21.3
Requires-Dist: orjson==3.11.0
Requires-Dist: overrides==7.7.0
Requires-Dist: py-asciimath==0.3.0
Requires-Dist: pyahocorasick==2.0.0
Requires-Dist: pydantic==2.11.7
Requires-Dist: pydantic-settings==2.10.1
Requires-Dist: pylatexenc==2.10
Requires-Dist: python-dotenv==1.1.1
Requires-Dist: python-multipart==0.0.20
Requires-Dist: scikit-learn>=1.6.1
Requires-Dist: selectolax==0.3.33
Requires-Dist: torch>=2.3.0
Requires-Dist: tqdm==4.67.1
Requires-Dist: transformers==4.40.2
Requires-Dist: uvicorn[standard]==0.35.0
Requires-Dist: xformers>=0.0.27
Provides-Extra: dev
Requires-Dist: flask==3.0.2; extra == "dev"
Requires-Dist: func_timeout==4.3.5; extra == "dev"
Requires-Dist: nbstripout==0.8.1; extra == "dev"
Requires-Dist: nltk==3.8.1; extra == "dev"
Requires-Dist: openai==1.75.0; extra == "dev"
Requires-Dist: pre-commit==3.8.0; extra == "dev"
Requires-Dist: pytest==8.3.3; extra == "dev"
Requires-Dist: pytest-cov==6.0.0; extra == "dev"
Requires-Dist: pytest-xdist==3.6.1; extra == "dev"
Requires-Dist: requests==2.31.0; extra == "dev"
Requires-Dist: retry==0.9.2; extra == "dev"
Dynamic: home-page
Dynamic: provides-extra
Dynamic: requires-dist
Dynamic: requires-python
Dynamic: summary
